AUTHORS.rst
CONTRIBUTING.rst
HISTORY.rst
LICENSE
MANIFEST.in
README.rst
setup.cfg
setup.py
docs/Makefile
docs/authors.rst
docs/conf.py
docs/contributing.rst
docs/history.rst
docs/index.rst
docs/installation.rst
docs/make.bat
docs/readme.rst
docs/usage.rst
grandcentral/__init__.py
grandcentral/grandcentral.py
grandcentral_py.egg-info/PKG-INFO
grandcentral_py.egg-info/SOURCES.txt
grandcentral_py.egg-info/dependency_links.txt
grandcentral_py.egg-info/not-zip-safe
grandcentral_py.egg-info/top_level.txt
tests/__init__.py
tests/test_grandcentral.py