Metadata-Version: 1.1
Name: grandcentral-py
Version: 0.1.0
Summary: GrandCentral is an extremely basic publisher subscriber event library
Home-page: https://github.com/kgritesh/grandcentral
Author: Ritesh Kadmawala
Author-email: k.g.ritesh@gmail.com
License: ISCL
Keywords: grandcentral
Platform: UNKNOWN
Classifier: Development Status :: 2 - Pre-Alpha
Classifier: Intended Audience :: Developers
Classifier: License :: OSI Approved :: ISC License (ISCL)
Classifier: Natural Language :: English
Classifier: Programming Language :: Python :: 2
Classifier: Programming Language :: Python :: 2.6
Classifier: Programming Language :: Python :: 2.7
Classifier: Programming Language :: Python :: 3
Classifier: Programming Language :: Python :: 3.3
Classifier: Programming Language :: Python :: 3.4
